tentaclio_databricks_pyodbc/__init__.py
tentaclio_databricks_pyodbc/__main__.py
tentaclio_databricks_pyodbc/clients/__init__.py
tentaclio_databricks_pyodbc/clients/databricks_client.py
tentaclio_databricks_pyodbc-0.0.2.dist-info/LICENSE.txt
tentaclio_databricks_pyodbc-0.0.2.dist-info/METADATA
tentaclio_databricks_pyodbc-0.0.2.dist-info/WHEEL
tentaclio_databricks_pyodbc-0.0.2.dist-info/top_level.txt
tentaclio_databricks_pyodbc-0.0.2.dist-info/RECORD
