Metadata-Version: 2.1
Name: tentaclio-databricks-pyodbc
Version: 0.0.2
Summary: A python project containing all the dependencies for schema databricks:pyodbc for tentaclio.
Home-page: UNKNOWN
Author: Octopus Energy
Author-email: nerds@octopus.energy
License: Proprietary
Platform: UNKNOWN
Classifier: Intended Audience :: Developers
Classifier: Operating System :: OS Independent
Classifier: Programming Language :: Python
Classifier: Programming Language :: Python :: 3
Classifier: Programming Language :: Python :: 3.6
Classifier: Programming Language :: Python :: 3.7
Classifier: Programming Language :: Python :: 3.8
Classifier: Programming Language :: Python :: 3.9
License-File: LICENSE.txt
Requires-Dist: sqlalchemy (<1.4.0)
Requires-Dist: pyodbc
Requires-Dist: psycopg2
